{
    "@schema": "https://raw.githubusercontent.com/slicer/slicer/master/Modules/Loadable/Markups/Resources/Schema/markups-schema-v1.0.0.json#",
    "markups": [
        {
            "type": "Line",
            "coordinateSystem": "LPS",
            "locked": false,
            "labelFormat": "%N-%d",
            "controlPoints": [
                {
                    "id": "1",
                    "label": "End",
                    "description": "",
                    "associatedNodeID": "vtkMRMLScalarVolumeNode1",
                    "position": [-250.6054582430369, -251.09551413265013, -0.00018883708946759725],
                    "orientation": [-1.0, -0.0, -0.0, -0.0, -1.0, -0.0, 0.0, 0.0, 1.0],
                    "selected": true,
                    "locked": false,
                    "visibility": true,
                    "positionStatus": "defined"
                },
                {
                    "id": "2",
                    "label": "Start",
                    "description": "",
                    "associatedNodeID": "vtkMRMLScalarVolumeNode1",
                    "position": [-423.2107813788275, -495.2926412456884, -0.00016527992841020023],
                    "orientation": [-1.0, -0.0, -0.0, -0.0, -1.0, -0.0, 0.0, 0.0, 1.0],
                    "selected": true,
                    "locked": false,
                    "visibility": true,
                    "positionStatus": "defined"
                }
            ],
            "measurements": [
                {
                    "name": "length",
                    "enabled": true,
                    "value": 34.7388507716887,
                    "printFormat": "%-#4.4gmm"
                }
            ],
            "display": {
                "visibility": true,
                "opacity": 1.0,
                "color": [0.5, 0.5, 0.5],
                "selectedColor": [1.0, 0.5000076295109484, 0.5000076295109484],
                "activeColor": [0.4, 1.0, 0.0],
                "propertiesLabelVisibility": true,
                "pointLabelsVisibility": false,
                "textScale": 3.0,
                "glyphType": "Sphere3D",
                "glyphScale": 1.0,
                "glyphSize": 5.0,
                "useGlyphScale": true,
                "sliceProjection": false,
                "sliceProjectionUseFiducialColor": true,
                "sliceProjectionOutlinedBehindSlicePlane": false,
                "sliceProjectionColor": [1.0, 1.0, 1.0],
                "sliceProjectionOpacity": 0.6,
                "lineThickness": 0.2,
                "lineColorFadingStart": 1.0,
                "lineColorFadingEnd": 10.0,
                "lineColorFadingSaturation": 1.0,
                "lineColorFadingHueOffset": 0.0,
                "handlesInteractive": false,
                "snapMode": "toVisibleSurface"
            }
        }
    ]
}